facecast_io/__init__.py
facecast_io/__main__.py
facecast_io/api.py
facecast_io/entities/__init__.py
facecast_io/entities/common.py
facecast_io/entities/device.py
facecast_io/entities/device_input.py
facecast_io/entities/device_output.py
facecast_io/entities/stream.py
facecast_io/errors.py
facecast_io/logger_setup.py
facecast_io/models.py
facecast_io/server_connector.py
facecast_io-0.5.1.dist-info/WHEEL
facecast_io-0.5.1.dist-info/METADATA
facecast_io-0.5.1.dist-info/RECORD
